pyminideprecator/__init__.py
pyminideprecator/config.py
pyminideprecator/deprecator.py
pyminideprecator/exc.py
pyminideprecator/py.typed
pyminideprecator/version.py
pyminideprecator-0.2.1.dist-info/METADATA
pyminideprecator-0.2.1.dist-info/WHEEL
pyminideprecator-0.2.1.dist-info/licenses/LICENSE
pyminideprecator-0.2.1.dist-info/RECORD
