Metadata-Version: 2.4
Name: pyminideprecator
Version: 0.2.1
Summary: Add your description here
Author-email: Alexeev Bronislav <alexeev.dev@mail.ru>
License-File: LICENSE
Requires-Python: >=3.10
Requires-Dist: asyncio<4.0.0,>=3.4.3
